<annotation>
	<folder>Tailorbird</folder>
	<filename>8481_Tailorbird.png</filename>
	<path>P:\Sid-Works\otherStuff\Yugam24\MLathon\Train_data\Tailorbird\8481_Tailorbird.png</path>
	<source>
		<database>Unknown</database>
	</source>
	<size>
		<width>800</width>
		<height>1200</height>
		<depth>3</depth>
	</size>
	<segmented>0</segmented>
	<object>
		<name>tailorbird</name>
		<pose>Unspecified</pose>
		<truncated>0</truncated>
		<difficult>0</difficult>
		<bndbox>
			<xmin>229</xmin>
			<ymin>456</ymin>
			<xmax>675</xmax>
			<ymax>676</ymax>
		</bndbox>
	</object>
</annotation>
